CHANGES.rst
CONTRIBUTORS.rst
DEVELOP.rst
LICENSE.rst
MANIFEST.in
README.rst
setup.cfg
setup.py
docs/conf.py
docs/index.rst
src/sixfeetup/__init__.py
src/sixfeetup.pmdashboard.egg-info/PKG-INFO
src/sixfeetup.pmdashboard.egg-info/SOURCES.txt
src/sixfeetup.pmdashboard.egg-info/dependency_links.txt
src/sixfeetup.pmdashboard.egg-info/entry_points.txt
src/sixfeetup.pmdashboard.egg-info/namespace_packages.txt
src/sixfeetup.pmdashboard.egg-info/not-zip-safe
src/sixfeetup.pmdashboard.egg-info/requires.txt
src/sixfeetup.pmdashboard.egg-info/top_level.txt
src/sixfeetup/pmdashboard/__init__.py
src/sixfeetup/pmdashboard/configure.zcml
src/sixfeetup/pmdashboard/interfaces.py
src/sixfeetup/pmdashboard/permissions.zcml
src/sixfeetup/pmdashboard/setuphandlers.py
src/sixfeetup/pmdashboard/testing.py
src/sixfeetup/pmdashboard/upgrades.py
src/sixfeetup/pmdashboard/upgrades.zcml
src/sixfeetup/pmdashboard/browser/__init__.py
src/sixfeetup/pmdashboard/browser/configure.zcml
src/sixfeetup/pmdashboard/browser/overrides/.gitkeep
src/sixfeetup/pmdashboard/browser/static/.gitkeep
src/sixfeetup/pmdashboard/browser/templates/client_view.pt
src/sixfeetup/pmdashboard/browser/templates/pmdashboard_view.pt
src/sixfeetup/pmdashboard/browser/templates/project_view.pt
src/sixfeetup/pmdashboard/locales/README.rst
src/sixfeetup/pmdashboard/locales/__init__.py
src/sixfeetup/pmdashboard/locales/sixfeetup.pmdashboard.pot
src/sixfeetup/pmdashboard/locales/update.py
src/sixfeetup/pmdashboard/locales/update.sh
src/sixfeetup/pmdashboard/locales/en/LC_MESSAGES/sixfeetup.pmdashboard.po
src/sixfeetup/pmdashboard/profiles/default/browserlayer.xml
src/sixfeetup/pmdashboard/profiles/default/catalog.xml
src/sixfeetup/pmdashboard/profiles/default/metadata.xml
src/sixfeetup/pmdashboard/profiles/default/registry.xml
src/sixfeetup/pmdashboard/profiles/default/rolemap.xml
src/sixfeetup/pmdashboard/profiles/uninstall/browserlayer.xml
src/sixfeetup/pmdashboard/tests/__init__.py
src/sixfeetup/pmdashboard/tests/test_robot.py
src/sixfeetup/pmdashboard/tests/test_setup.py
src/sixfeetup/pmdashboard/tests/robot/test_example.robot